roman_lcs/__init__.py
roman_lcs/machine.py
roman_lcs/perturbation.py
roman_lcs/roman.py
roman_lcs/utils.py
roman_lcs-0.4.1.dist-info/METADATA
roman_lcs-0.4.1.dist-info/WHEEL
roman_lcs-0.4.1.dist-info/licenses/LICENSE
roman_lcs-0.4.1.dist-info/RECORD
