Metadata-Version: 2.4
Name: roman-lcs
Version: 0.4.1
Summary: Tools to compute PSF photometry with Roman simulated data
License: MIT
License-File: LICENSE
Author: Jorge Martinez-Palomera
Author-email: jorgemarpa@ug.uchile.cl
Requires-Python: >=3.10,<4.0
Classifier: License :: OSI Approved :: MIT License
Classifier: Programming Language :: Python :: 3
Classifier: Programming Language :: Python :: 3.10
Classifier: Programming Language :: Python :: 3.11
Classifier: Programming Language :: Python :: 3.12
Classifier: Programming Language :: Python :: 3.13
Classifier: Programming Language :: Python :: 3.14
Requires-Dist: astropy (>5,<7)
Requires-Dist: fitsio (>=1.1.3,<2.0.0)
Requires-Dist: lightkurve (>=2.0,<3.0)
Requires-Dist: matplotlib (>=3.3.3)
Requires-Dist: numpy (>=1.26.4,<2.0.0)
Requires-Dist: pandas (>1.5,<3.0)
Requires-Dist: patsy (>=0.5.1,<0.6.0)
Requires-Dist: roman-cuts (>=0.3.0)
Requires-Dist: scipy (>=1.9.0,<2.0.0)
Requires-Dist: tqdm (>=4.54,<5.0)
